<?xml version="1.0" encoding="utf-8"?>
<!DOCTYPE datafile PUBLIC "-//Logiqx//DTD ROM Management Datafile//EN" "http://www.logiqx.com/Dats/datafile.dtd">
<datafile>
	<header>
		<id>006</id>
		<name>006 - Lost Level Archive - Nintendo - Game Boy Color</name>
		<description>Nintendo - Game Boy Color</description>
		<version>v20250201</version>
		<author>tele</author>
		<homepage>Lost Level Archive</homepage>
		<url>https://www.github.com/televandalist/lost-level-archive</url>
		<clrmamepro forcenodump="required"/>
	</header>
	<game name="Best Text Adventure, The (World) (Aftermarket) (Unl)">
		<description>Best Text Adventure, The (World) (Aftermarket) (Unl)</description>
		<rom name="Best Text Adventure, The (World) (Aftermarket) (Unl).gbc" size="1048576" crc="7b13d437" md5="e15744f9e33180f5825c0242900f5a89" sha1="6689a6180096160a44349338e29f2002f2f26da1" />
	</game>
	<game name="Castlevania - Circle of the Moon - GBC Edition (World) (v2.0) (Aftermarket) (Unl)">
		<description>Castlevania - Circle of the Moon - GBC Edition (World) (v2.0) (Aftermarket) (Unl)</description>
		<rom name="Castlevania - Circle of the Moon - GBC Edition (World) (v2.0) (Aftermarket) (Unl).gbc" size="262144" crc="5312f81c" md5="4daf9a94ff78252257e22a34516e5105" sha1="05d553049a1ba1999e5891097471bff1b882cee7" />
	</game>
	<game name="Combo Fishing (World) (Aftermarket) (Unl)">
		<description>Combo Fishing (World) (Aftermarket) (Unl)</description>
		<rom name="Combo Fishing (World) (Aftermarket) (Unl).gbc" size="524288" crc="5c307010" md5="029cd8ae6b130b91918597239464cc35" sha1="61217782f0947a6c947c8a12eff12a8b9ce6d120" />
	</game>
	<game name="Dangan GB2 (World) (Aftermarket) (Unl)">
		<description>Dangan GB2 (World) (Aftermarket) (Unl</description>
		<rom name="Dangan GB2 (World) (Aftermarket) (Unl).gbc" size="524288" crc="c5d3d66a" md5="82ab96cba5233ec4a07cf21d81e625b7" sha1="a8f61ff5049e19b1b30a29bf9d996cb40b1f55c3" />
	</game>
	<game name="Date with Falco (World) (v1.0) (Aftermarket) (Unl)">
		<description>Date with Falco (World) (v1.0) (Aftermarket) (Unl)</description>
		<rom name="Date with Falco (World) (v1.0) (Aftermarket) (Unl).gbc" size="524288" crc="bd513f20" md5="1145a60834a2f5910559e33cde6b6d1a" sha1="58cf2e1959e2c563117cf3c47017f4b9a94f4df2" />
	</game>
	<game name="Days Without - Elvies [More Endings] (World) (Aftermarket) (Unl)">
		<description>Days Without - Elvies [More Endings] (World) (Aftermarket) (Unl)</description>
		<rom name="Days Without - Elvies [More Endings] (World) (Aftermarket) (Unl).gbc" size="262144" crc="f771966a" md5="a51e8561778943f794942070f137ecb6" sha1="6d8463829db7307fbf7f9d562678edf2ead0a123" />
	</game>
	<game name="Enceladus (World) (v3.0) (GBCompo2023) (Aftermarket) (Unl)">
		<description>Enceladus (World) (v3.0) (GBCompo2023) (Aftermarket) (Unl)</description>
		<rom name="Enceladus (World) (v3.0) (GBCompo2023) (Aftermarket) (Unl).gbc" size="524288" crc="5322fa2b" md5="70b4c73e34c53ac818d15daa6682c396" sha1="355e76f7cf46b383320eb3ad8e40fc1db58f9ad1" />
	</game>
	<game name="Five Nights at Freddy's (World) (v0.5) (Aftermarket) (Unl)">
		<description>Five Nights at Freddy's (World) (v0.5) (Aftermarket) (Unl)</description>
		<rom name="Five Nights at Freddy's (World) (v0.5) (Aftermarket) (Unl).gbc" size="524288" crc="b5d08d14" md5="59e32f8c38b3400bc147a470c88fb582" sha1="cbb21e03b63f72648ac3dfbc5fc5818fd15b6d3c" />
	</game>
	<game name="G-ZERO World GP (World) (v1.0) (Aftermarket) (Unl)">
		<description>G-ZERO World GP (World) (v1.0) (Aftermarket) (Unl)</description>
		<rom name="G-ZERO World GP (World) (v1.0) (Aftermarket) (Unl).gbc" size="262144" crc="2f813033" md5="3e151d9bfd7b36a80ef475a98863a001" sha1="0407a3fc4c8c6711cde8fe9d07860dc3ef075f5e" />
	</game>
	<game name="Hatsune Miku Bomb Squad (World) (v1.3) (Aftermarket) (Unl)">
		<description>Hatsune Miku Bomb Squad (World) (v1.3) (Aftermarket) (Unl)</description>
		<rom name="Hatsune Miku Bomb Squad (World) (v1.3) (Aftermarket) (Unl).gbc" size="524288" crc="b5465484" md5="6364d4ca7ea0f83981e97c12fd08ea97" sha1="4592070930a50e7f21ec10ecf0ef3d2365aec9a7" />
	</game>
	<game name="Hong Kong 2099 (World) (Aftermarket) (Unl)">
		<description>Hong Kong 2099 (World) (Aftermarket) (Unl)</description>
		<rom name="Hong Kong 2099 (World) (Aftermarket) (Unl).gbc" size="524288" crc="28f9e064" md5="c1dd8c5952ea02286616d3ff0d8c54cb" sha1="ee17c7e334d17a78bd120c1de41a7020b57344db" />
	</game>
	<game name="Inventory Full (World) (v1.0.3) (Aftermarket) (Unl)">
		<description>Inventory Full (World) (v1.0.3) (Aftermarket) (Unl)</description>
		<rom name="Inventory Full (World) (v1.0.3) (Aftermarket) (Unl).gbc" size="524288" crc="36174683" md5="e9bf8b6977020c869dc5f2d3304961c2" sha1="ff5fc33f6009a8819c6cbde00174c074aab3ecef" />
	</game>
	<game name="Karpe Diem (World) (v1.0) (Aftermarket) (Unl)">
		<description>Karpe Diem (World) (v1.0) (Aftermarket) (Unl)</description>
		<rom name="Karpe Diem (World) (v1.0) (Aftermarket) (Unl).gbc" size="524288" crc="91cc7412" md5="c3ff18fa6209d7302f91948b1ae42843" sha1="94a85b63a7340a03d3e8e41fda45408b4cb2ba3b" />
	</game>
	<game name="Knights of the Zodiac - The Phoenix Returns (World) (En) (v1.3.0) (Aftermarket) (Unl)">
		<description>Knights of the Zodiac - The Phoenix Returns (World) (En) (v1.3.0) (Aftermarket) (Unl)</description>
		<rom name="Knights of the Zodiac - The Phoenix Returns (World) (En) (v1.3.0) (Aftermarket) (Unl).gbc" size="4194304" crc="a52b5270" md5="fc0712c84209785a3a78e6a04dc5b89c" sha1="282667fe2652645b4f999e71a127a708f0fcd7cb" />
	</game>
	<game name="Knights of the Zodiac - The Phoenix Returns (World) (Es) (v1.4.0) (Aftermarket) (Unl)" cloneof="Knights of the Zodiac - The Phoenix Returns (World) (En) (v1.3.0) (Aftermarket) (Unl)">
		<description>Knights of the Zodiac - The Phoenix Returns (World) (Es) (v1.4.0) (Aftermarket) (Unl)</description>
		<rom name="Knights of the Zodiac - The Phoenix Returns (World) (Es) (v1.4.0) (Aftermarket) (Unl).gbc" size="4194304" crc="c9b24ad0" md5="fa6561096455baa88b399164b676496b" sha1="4ca502dd3f252d033a9c633b93a3f85521acffb0" />
	</game>
	<game name="Knights of the Zodiac - The Phoenix Returns (World) (Es) (v1.4.1) (Aftermarket) (Unl)" cloneof="Knights of the Zodiac - The Phoenix Returns (World) (En) (v1.3.0) (Aftermarket) (Unl)">
		<description>Knights of the Zodiac - The Phoenix Returns (World) (Es) (v1.4.1) (Aftermarket) (Unl)</description>
		<rom name="Knights of the Zodiac - The Phoenix Returns (World) (Es) (v1.4.1) (Aftermarket) (Unl).gbc" size="4194304" crc="60f85669" md5="7acc4ab4a83726cd2873271f82ef3f63" sha1="415e48abc0de4c0cc87e676471baad0382149b7d" />
	</game>
	<game name="Knights of the Zodiac - The Phoenix Returns (World) (Fr) (v1.2.1) (Aftermarket) (Unl)" cloneof="Knights of the Zodiac - The Phoenix Returns (World) (En) (v1.3.0) (Aftermarket) (Unl)">
		<description>Knights of the Zodiac - The Phoenix Returns (World) (Fr) (v1.2.1) (Aftermarket) (Unl)</description>
		<rom name="Knights of the Zodiac - The Phoenix Returns (World) (Fr) (v1.2.1) (Aftermarket) (Unl).gbc" size="4194304" crc="25929c86" md5="f79c225fbc24ff9844d5b2f012a8541e" sha1="62cd97ceaed79c33d57a106f098744510d8d3184" />
	</game>
	<game name="Knights of the Zodiac - The Phoenix Returns (World) (It) (v1.2.0) (Aftermarket) (Unl)" cloneof="Knights of the Zodiac - The Phoenix Returns (World) (En) (v1.3.0) (Aftermarket) (Unl)">
		<description>Knights of the Zodiac - The Phoenix Returns (World) (It) (v1.2.0) (Aftermarket) (Unl)</description>
		<rom name="Knights of the Zodiac - The Phoenix Returns (World) (It) (v1.2.0) (Aftermarket) (Unl).gbc" size="4194304" crc="9ff6e42d" md5="3ca37ba893d5795af2c6b9b6563126a2" sha1="9513949d6ec549b9f2aac03af32f412e00462fee" />
	</game>
	<game name="Knights of the Zodiac - The Phoenix Returns (World) (Pt) (v1.2.0) (Aftermarket) (Unl)" cloneof="Knights of the Zodiac - The Phoenix Returns (World) (En) (v1.3.0) (Aftermarket) (Unl)">
		<description>Knights of the Zodiac - The Phoenix Returns (World) (Pt) (v1.2.0) (Aftermarket) (Unl)</description>
		<rom name="Knights of the Zodiac - The Phoenix Returns (World) (Pt) (v1.2.0) (Aftermarket) (Unl).gbc" size="4194304" crc="0c6cdaaa" md5="a208b6e3cea582b1e45255031b6b7152" sha1="2e28c460be56eaeae975f620c66228e1cf66b1ed" />
	</game>
	<game name="Little Dungeon Renovator (World) (v1.0) (GBCompo2023) (Aftermarket) (Unl)">
		<description>Little Dungeon Renovator (World) (v1.0) (GBCompo2023) (Aftermarket) (Unl)</description>
		<rom name="Little Dungeon Renovator (World) (v1.0) (GBCompo2023) (Aftermarket) (Unl).gbc" size="262144" crc="d20ab5bd" md5="c93bd5f1928944452cee933dce345f89" sha1="215180e6d2482f3208315fb17a35830c6560133e" />
	</game>
	<game name="Mandalorian, The - Chapter 3 - The Sin (World) (v2.1) (World) (Aftermarket) (Unl)">
		<description>Mandalorian, The - Chapter 3 - The Sin (World) (v2.1) (World) (Aftermarket) (Unl)</description>
		<rom name="Mandalorian, The - Chapter 3 - The Sin (World) (v2.1) (World) (Aftermarket) (Unl).gbc" size="524288" crc="1d758544" md5="91c3d238305f308e00fca917d996bb40" sha1="644a6409949520b1c7a654eed6a156d35967ec1c" />
	</game>
	<game name="Metroid Dread Demake (World) (v1.0) (Aftermarket) (Unl)">
		<description>Metroid Dread Demake (World) (v1.0) (Aftermarket) (Unl)</description>
		<rom name="Metroid Dread Demake (World) (v1.0) (Aftermarket) (Unl).gbc" size="262144" crc="858bab79" md5="b694cf3747aea6ac213cf2401f0ad421" sha1="a49810d37a58b02ed5af7cd9a07b54d93f812223" />
	</game>
	<game name="Mina the Hollower GBC Demake (World) (Aftermarket) (Unl)">
		<description>Mina the Hollower GBC Demake (World) (Aftermarket) (Unl)</description>
		<rom name="Mina the Hollower GBC Demake (World) (Aftermarket) (Unl).gbc" size="262144" crc="66af8f9e" md5="ae74b0c434f0097cfd674a66d47062cc" sha1="1d1f073fef78599f8074c80c24a1b8ea72f78361" />
	</game>
	<game name="Mist, The (World) (v1.3.3) (Aftermarket) (Unl)">
		<description>Mist, The (World) (v1.3.3) (Aftermarket) (Unl)</description>
		<rom name="Mist, The (World) (v1.3.3) (Aftermarket) (Unl).gbc" size="524288" crc="f088ffbd" md5="dafb6629c51cdf4bb11f9b6154321aa0" sha1="6d10498e8d7934d7b481118760fdb62469fba07b" />
	</game>
	<game name="My Saturday Grounded (World) (v2.0) (Aftermarket) (Unl)">
		<description>My Saturday Grounded (World) (v2.0) (Aftermarket) (Unl)</description>
		<rom name="My Saturday Grounded (World) (v2.0) (Aftermarket) (Unl).gbc" size="262144" crc="703ad0bc" md5="02d5f8a622ba5255eb544fc38ef81728" sha1="f3f7931255ef2279e632ec12a86236cb05169095" />
	</game>
	<game name="Noble Blood (World) (Shacknews Jam Fall 2023) (Aftermarket) (Unl)">
		<description>Noble Blood (World) (Shacknews Jam Fall 2023) (Aftermarket) (Unl)</description>
		<rom name="Noble Blood (World) (Shacknews Jam Fall 2023) (Aftermarket) (Unl).gbc" size="262144" crc="703c466b" md5="aaafb103c5c85e50a024b61e14f30497" sha1="49533d91ea8e40dbf716b7e4e879a6f8164d5ae8" />
	</game>
	<game name="Remote Control Shuriken (World) (GBCompo2021) (Aftermarket) (Unl)">
		<description>Remote Control Shuriken (World) (GBCompo2021) (Aftermarket) (Unl)</description>
		<rom name="Remote Control Shuriken (World) (GBCompo2021) (Aftermarket) (Unl).gbc" size="131072" crc="16f444cf" md5="09ec8f62034f0219e0a82e3f01f48ba7" sha1="cdfc9441ea05b1ba5312c7b4fc5d7df21d74cd31" />
	</game>
	<game name="Rezal (World) (GBA Jam 2024) (Aftermarket) (Unl)">
		<description>Rezal (World) (GBA Jam 2024) (Aftermarket) (Unl)</description>
		<rom name="Rezal (World) (GBA Jam 2024) (Aftermarket) (Unl).gbc" size="262144" crc="c5048c76" md5="9a5ca9da453a74e3e6745eecea8a009d" sha1="e2489ac617078504443ee2e468e62fec8ca81744" />
	</game>
	<game name="Rick Astley - The Game (World) (En,Fr) (v20211212) (Aftermarket) (Unl)">
		<description>Rick Astley - The Game (World) (En,Fr) (v20211212) (Aftermarket) (Unl)</description>
		<rom name="Rick Astley - The Game (World) (En,Fr) (v20211212) (Aftermarket) (Unl).gbc" size="262144" crc="7caeefc9" md5="93d2d9acc1e9cd454ccb575100ce5070" sha1="cb97fb2041a732fe9bae7647294502fc7befee18" />
	</game>
	<game name="Skinner &amp; the Superintendent (World) (En) (v1.0) (Aftermarket) (Unl)">
		<description>Skinner &amp; the Superintendent (World) (En) (v1.0) (Aftermarket) (Unl)</description>
		<rom name="Skinner &amp; the Superintendent (World) (En) (v1.0) (Aftermarket) (Unl).gbc" size="524288" crc="c620e4e6" md5="df2e5192e40caf52dd514895255fd5e5" sha1="546ff05f5803a31936c403988b36a804ad1dccd7" />
	</game>
	<game name="Skinner &amp; the Superintendent (World) (Pt) (v1.0) (Aftermarket) (Unl)" cloneof="Skinner &amp; the Superintendent (World) (En) (v1.0) (Aftermarket) (Unl)">
		<description>Skinner &amp; the Superintendent (World) (Pt) (v1.0) (Aftermarket) (Unl)</description>
		<rom name="Skinner &amp; the Superintendent (World) (Pt) (v1.0) (Aftermarket) (Unl).gbc" size="524288" crc="bce552a7" md5="ea90aa4b07d6e1e43434b1ed1b471f4e" sha1="a6a6e3fef9bd3d8344229b9654c8ee8c88f6a864" />
	</game>
	<game name="Slender - The 8 Pages (World) (Aftermarket) (Unl)">
		<description>Slender - The 8 Pages (World) (Aftermarket) (Unl)</description>
		<rom name="Slender - The 8 Pages (World) (Aftermarket) (Unl).gbc" size="524288" crc="350f7fe6" md5="4165032fb478ebda7e15d35deb5937a8" sha1="e864bd35bf80cf03a45f39111a6b9648df8b7f46" />
	</game>
	<game name="Super Doggo WOW WAN (World) (Aftermarket) (Unl)">
		<description>Super Doggo WOW WAN (World) (Aftermarket) (Unl)</description>
		<rom name="Super Doggo WOW WAN (World) (Aftermarket) (Unl).gbc" size="1048576" crc="02111d9d" md5="b9032a7c44305f4fbba30891427c03fb" sha1="ad86d1447d5d2588a1d9b7af080a14957dcf3bd6" />
	</game>
	<game name="Super Mario Bros. Mini (World) (v2.0.8) (Aftermarket) (Unl)">
		<description>Super Mario Bros. Mini (World) (v2.0.8) (Aftermarket) (Unl)</description>
		<rom name="Super Mario Bros. Mini (World) (v2.0.8) (Aftermarket) (Unl).gbc" size="2097152" crc="c2bfe433" md5="14a2442e6b50b2617e58ffe10ed6a970" sha1="c9eee8d916390e3bd6142370de4d9fe501fd44a8" />
	</game>
	<game name="Taiyaki Fabulous Museum of Fish (World) (v1.4.2) (Aftermarket) (Unl)">
		<description>Taiyaki Fabulous Museum of Fish (World) (v1.4.2) (Aftermarket) (Unl)</description>
		<rom name="Taiyaki Fabulous Museum of Fish (World) (v1.4.2) (Aftermarket) (Unl).gbc" size="2097152" crc="2d12223c" md5="9b3077bf785168c3d19d05173c443421" sha1="940ec098d7df6db344b253f713d193ed01cb1219" />
	</game>
	<game name="TUNIC (World) (v1.1) (Aftermarket) (Unl)">
		<description>TUNIC (World) (v1.1) (Aftermarket) (Unl)</description>
		<rom name="TUNIC (World) (v1.1) (Aftermarket) (Unl).gbc" size="524288" crc="4dc4e4a0" md5="5d92f768e7b8d371cc3aac98b3b6a2fe" sha1="cc8a01118c25332b506a380b78c95a5876c17459" />
	</game>
	<game name="Wishing Sarah (World) (En) (v1.1) (Aftermarket) (Unl)">
		<description>Wishing Sarah (World) (En) (v1.1) (Aftermarket) (Unl)</description>
		<rom name="Wishing Sarah (World) (En) (v1.1) (Aftermarket) (Unl).gbc" size="524288" crc="efa345cd" md5="83e0f56f6315f46aaf4e7b77576b00e9" sha1="0e32eb4ef5cc3c456072892c376c5ee5d4fc78f1" />
	</game>
	<game name="Wishing Sarah (World) (PT-BR) (v1.1) (Aftermarket) (Unl)" cloneof="Wishing Sarah (World) (En) (v1.1) (Aftermarket) (Unl)">
		<description>Wishing Sarah (World) (PT-BR) (v1.1) (Aftermarket) (Unl)</description>
		<rom name="Wishing Sarah (World) (PT-BR) (v1.1) (Aftermarket) (Unl).gbc" size="524288" crc="ab6cf21e" md5="f7eba1c53b02624852daea423a71c4ea" sha1="575b8b0f6fdb2d41623e7f2fe9902c87236f1a36" />
	</game>
</datafile>